{
  "roots": [
    {
      "key": "zkfccjgcs7b7pqvirwby57p",
      "title": "Web Components",
      "icon": null,
      "hasTitleNumberOutlined": false,
      "vaultName": "docs",
      "children": [
        {
          "key": "3902657y6cqngtzx4irs133",
          "title": "Apis",
          "icon": null,
          "hasTitleNumberOutlined": false,
          "vaultName": "docs",
          "children": [
            {
              "key": "1dym5u9edx4r2i85mmldv4m",
              "title": "custom-elements",
              "icon": null,
              "hasTitleNumberOutlined": false,
              "vaultName": "docs",
              "children": []
            },
            {
              "key": "efwvmwe8ctv925mkt5wrl5z",
              "title": "shadow-dom",
              "icon": null,
              "hasTitleNumberOutlined": false,
              "vaultName": "docs",
              "children": []
            },
            {
              "key": "d9i2loe47cp2m0xxwdkny69",
              "title": "content-slot",
              "icon": null,
              "hasTitleNumberOutlined": false,
              "vaultName": "docs",
              "children": []
            },
            {
              "key": "lf0t5f3evkower2vnkbazq5",
              "title": "template",
              "icon": null,
              "hasTitleNumberOutlined": false,
              "vaultName": "docs",
              "children": []
            }
          ]
        },
        {
          "key": "jz2mgtp1h1frnrzmeqocl36",
          "title": "Communication",
          "icon": null,
          "hasTitleNumberOutlined": false,
          "vaultName": "docs",
          "children": [
            {
              "key": "6ru1efirtn5teux1y43551d",
              "title": "JS Properties",
              "icon": null,
              "hasTitleNumberOutlined": false,
              "vaultName": "docs",
              "children": []
            },
            {
              "key": "tnijj658ufqhea7vlwft2r9",
              "title": "Custom Attributes",
              "icon": null,
              "hasTitleNumberOutlined": false,
              "vaultName": "docs",
              "children": []
            },
            {
              "key": "h8e4ccyda8x2xn10jqv3qb2",
              "title": "Events",
              "icon": null,
              "hasTitleNumberOutlined": false,
              "vaultName": "docs",
              "children": []
            }
          ]
        },
        {
          "key": "f1sy95vvl2cyfpto8miwxhh",
          "title": "Styling",
          "icon": null,
          "hasTitleNumberOutlined": false,
          "vaultName": "docs",
          "children": [
            {
              "key": "fcj7t4u5hm6t7amh45uid1n",
              "title": "CSS Encapsulation",
              "icon": null,
              "hasTitleNumberOutlined": false,
              "vaultName": "docs",
              "children": []
            },
            {
              "key": "5vihc22zv3ux3lduf3aaab6",
              "title": "CSS Custom Properties",
              "icon": null,
              "hasTitleNumberOutlined": false,
              "vaultName": "docs",
              "children": []
            },
            {
              "key": "lgs19vv9v8nq2megefqyprn",
              "title": "CSS Parts API",
              "icon": null,
              "hasTitleNumberOutlined": false,
              "vaultName": "docs",
              "children": []
            },
            {
              "key": "3lzfo9vm01y09nvjbji1g25",
              "title": "Slotted Elements",
              "icon": null,
              "hasTitleNumberOutlined": false,
              "vaultName": "docs",
              "children": []
            }
          ]
        },
        {
          "key": "wulm1e3c9d69le8k1pa5lxh",
          "title": "Theming",
          "icon": null,
          "hasTitleNumberOutlined": false,
          "vaultName": "docs",
          "children": [
            {
              "key": "kguufsu71atg67ixw875jy1",
              "title": "Root Host Scope",
              "icon": null,
              "hasTitleNumberOutlined": false,
              "vaultName": "docs",
              "children": []
            }
          ]
        },
        {
          "key": "gxmnngmtnylxfipxr0980ej",
          "title": "Lifecycle",
          "icon": null,
          "hasTitleNumberOutlined": false,
          "vaultName": "docs",
          "children": [
            {
              "key": "uw1ie7bctc50l5lz3cytw4i",
              "title": "Constructor Connected Callback",
              "icon": null,
              "hasTitleNumberOutlined": false,
              "vaultName": "docs",
              "children": []
            },
            {
              "key": "37nsf4f13y89b6j5pgbmd9o",
              "title": "Attribute Changed",
              "icon": null,
              "hasTitleNumberOutlined": false,
              "vaultName": "docs",
              "children": []
            },
            {
              "key": "u5xmw029xvzv9yc7s3o152j",
              "title": "Disconnected Callback",
              "icon": null,
              "hasTitleNumberOutlined": false,
              "vaultName": "docs",
              "children": []
            },
            {
              "key": "iqbswjrdrlwkkca05u33nov",
              "title": "Adopted Callback",
              "icon": null,
              "hasTitleNumberOutlined": false,
              "vaultName": "docs",
              "children": []
            }
          ]
        },
        {
          "key": "a3xw0se9vtlbizvaguc85sw",
          "title": "Hierarchy and Architecture",
          "icon": null,
          "hasTitleNumberOutlined": false,
          "vaultName": "docs",
          "children": [
            {
              "key": "nz23kt8zcx99qr9ei3td0kg",
              "title": "Component Data Flow",
              "icon": null,
              "hasTitleNumberOutlined": false,
              "vaultName": "docs",
              "children": []
            }
          ]
        },
        {
          "key": "1mhjcs0yb8e8xp0x1g030qq",
          "title": "Deployment",
          "icon": null,
          "hasTitleNumberOutlined": false,
          "vaultName": "docs",
          "children": [
            {
              "key": "pizkajsyb0lra3nyjuiueiq",
              "title": "Npm",
              "icon": null,
              "hasTitleNumberOutlined": false,
              "vaultName": "docs",
              "children": []
            },
            {
              "key": "l1ofcgjdkle0j55lk21ujrq",
              "title": "Browser Support",
              "icon": null,
              "hasTitleNumberOutlined": false,
              "vaultName": "docs",
              "children": []
            }
          ]
        },
        {
          "key": "hgfihscw1sv5ewje8sm80r9",
          "title": "Frameworks Integration",
          "icon": null,
          "hasTitleNumberOutlined": false,
          "vaultName": "docs",
          "children": [
            {
              "key": "3m8fv43uyem4l9uc3y7780z",
              "title": "Angular",
              "icon": null,
              "hasTitleNumberOutlined": false,
              "vaultName": "docs",
              "children": []
            },
            {
              "key": "tqrfdzuafg2zfze5bj19sns",
              "title": "React",
              "icon": null,
              "hasTitleNumberOutlined": false,
              "vaultName": "docs",
              "children": []
            },
            {
              "key": "95mp2snular2q0j2irih6ht",
              "title": "Vue",
              "icon": null,
              "hasTitleNumberOutlined": false,
              "vaultName": "docs",
              "children": []
            }
          ]
        },
        {
          "key": "09edenuzuoqp22bxje5l36y",
          "title": "High Level Solutions",
          "icon": null,
          "hasTitleNumberOutlined": false,
          "vaultName": "docs",
          "children": [
            {
              "key": "ik9twe6vf70yht7mt79j88t",
              "title": "Lit",
              "icon": null,
              "hasTitleNumberOutlined": false,
              "vaultName": "docs",
              "children": [
                {
                  "key": "n0j2ootma2fifoxdm24zs2e",
                  "title": "Binding Components",
                  "icon": null,
                  "hasTitleNumberOutlined": false,
                  "vaultName": "docs",
                  "children": []
                },
                {
                  "key": "nx5lgbcvbdsmx43eu1jujpt",
                  "title": "Custom Events",
                  "icon": null,
                  "hasTitleNumberOutlined": false,
                  "vaultName": "docs",
                  "children": []
                },
                {
                  "key": "218js88kimcujeri1kdql6t",
                  "title": "Examples",
                  "icon": "plusOutlined",
                  "hasTitleNumberOutlined": false,
                  "vaultName": "docs",
                  "children": [
                    {
                      "key": "q73ywmrtq7srqjbs0jjzxm2",
                      "title": "Todo App",
                      "icon": null,
                      "hasTitleNumberOutlined": false,
                      "vaultName": "docs",
                      "children": []
                    },
                    {
                      "key": "jnfxsw50aav1bist3xdmb36",
                      "title": "Unit Testing",
                      "icon": null,
                      "hasTitleNumberOutlined": false,
                      "vaultName": "docs",
                      "children": []
                    }
                  ]
                },
                {
                  "key": "w9h2yeqs0gc5da00dbw690j",
                  "title": "Properties and Decorators",
                  "icon": null,
                  "hasTitleNumberOutlined": false,
                  "vaultName": "docs",
                  "children": []
                },
                {
                  "key": "o7lmvujajn5mr0cyficoef5",
                  "title": "Template Event Listeners",
                  "icon": null,
                  "hasTitleNumberOutlined": false,
                  "vaultName": "docs",
                  "children": []
                },
                {
                  "key": "ex5lcezatpfmu8p97fgbey7",
                  "title": "Template Strings",
                  "icon": null,
                  "hasTitleNumberOutlined": false,
                  "vaultName": "docs",
                  "children": []
                }
              ]
            },
            {
              "key": "gl5xjjjpsuuiazam6swp1qp",
              "title": "Stencil",
              "icon": null,
              "hasTitleNumberOutlined": false,
              "vaultName": "docs",
              "children": [
                {
                  "key": "peaxf97kpd4jafg9wekcaz8",
                  "title": "Building",
                  "icon": null,
                  "hasTitleNumberOutlined": false,
                  "vaultName": "docs",
                  "children": []
                },
                {
                  "key": "s3mhgxb78z7jyifmzp1hsd3",
                  "title": "Component Bindings",
                  "icon": null,
                  "hasTitleNumberOutlined": false,
                  "vaultName": "docs",
                  "children": []
                },
                {
                  "key": "grym4gsk3se3limyrf8uoip",
                  "title": "Decorators",
                  "icon": null,
                  "hasTitleNumberOutlined": false,
                  "vaultName": "docs",
                  "children": []
                },
                {
                  "key": "3x98jnnbdtk4yacyr4wpefc",
                  "title": "JSX Templates",
                  "icon": null,
                  "hasTitleNumberOutlined": false,
                  "vaultName": "docs",
                  "children": []
                }
              ]
            }
          ]
        },
        {
          "key": "a4d445e0o55ndcozlhkwqfz",
          "title": "Examples",
          "icon": null,
          "hasTitleNumberOutlined": false,
          "vaultName": "docs",
          "children": [
            {
              "key": "olp8vo3frywt998l6h1f3ws",
              "title": "Dropdown",
              "icon": null,
              "hasTitleNumberOutlined": false,
              "vaultName": "docs",
              "children": []
            }
          ]
        },
        {
          "key": "0qxb469esdfnckmc3254mmp",
          "title": "Extra Tools",
          "icon": null,
          "hasTitleNumberOutlined": false,
          "vaultName": "docs",
          "children": [
            {
              "key": "m75y7l3tusc1xrp3atjv1jz",
              "title": "Webpack",
              "icon": null,
              "hasTitleNumberOutlined": false,
              "vaultName": "docs",
              "children": []
            }
          ]
        }
      ]
    }
  ],
  "child2parent": {
    "zkfccjgcs7b7pqvirwby57p": null,
    "3902657y6cqngtzx4irs133": "zkfccjgcs7b7pqvirwby57p",
    "1dym5u9edx4r2i85mmldv4m": "3902657y6cqngtzx4irs133",
    "efwvmwe8ctv925mkt5wrl5z": "3902657y6cqngtzx4irs133",
    "d9i2loe47cp2m0xxwdkny69": "3902657y6cqngtzx4irs133",
    "lf0t5f3evkower2vnkbazq5": "3902657y6cqngtzx4irs133",
    "jz2mgtp1h1frnrzmeqocl36": "zkfccjgcs7b7pqvirwby57p",
    "6ru1efirtn5teux1y43551d": "jz2mgtp1h1frnrzmeqocl36",
    "tnijj658ufqhea7vlwft2r9": "jz2mgtp1h1frnrzmeqocl36",
    "h8e4ccyda8x2xn10jqv3qb2": "jz2mgtp1h1frnrzmeqocl36",
    "f1sy95vvl2cyfpto8miwxhh": "zkfccjgcs7b7pqvirwby57p",
    "fcj7t4u5hm6t7amh45uid1n": "f1sy95vvl2cyfpto8miwxhh",
    "5vihc22zv3ux3lduf3aaab6": "f1sy95vvl2cyfpto8miwxhh",
    "lgs19vv9v8nq2megefqyprn": "f1sy95vvl2cyfpto8miwxhh",
    "3lzfo9vm01y09nvjbji1g25": "f1sy95vvl2cyfpto8miwxhh",
    "wulm1e3c9d69le8k1pa5lxh": "zkfccjgcs7b7pqvirwby57p",
    "kguufsu71atg67ixw875jy1": "wulm1e3c9d69le8k1pa5lxh",
    "gxmnngmtnylxfipxr0980ej": "zkfccjgcs7b7pqvirwby57p",
    "uw1ie7bctc50l5lz3cytw4i": "gxmnngmtnylxfipxr0980ej",
    "37nsf4f13y89b6j5pgbmd9o": "gxmnngmtnylxfipxr0980ej",
    "u5xmw029xvzv9yc7s3o152j": "gxmnngmtnylxfipxr0980ej",
    "iqbswjrdrlwkkca05u33nov": "gxmnngmtnylxfipxr0980ej",
    "a3xw0se9vtlbizvaguc85sw": "zkfccjgcs7b7pqvirwby57p",
    "nz23kt8zcx99qr9ei3td0kg": "a3xw0se9vtlbizvaguc85sw",
    "1mhjcs0yb8e8xp0x1g030qq": "zkfccjgcs7b7pqvirwby57p",
    "pizkajsyb0lra3nyjuiueiq": "1mhjcs0yb8e8xp0x1g030qq",
    "l1ofcgjdkle0j55lk21ujrq": "1mhjcs0yb8e8xp0x1g030qq",
    "hgfihscw1sv5ewje8sm80r9": "zkfccjgcs7b7pqvirwby57p",
    "3m8fv43uyem4l9uc3y7780z": "hgfihscw1sv5ewje8sm80r9",
    "tqrfdzuafg2zfze5bj19sns": "hgfihscw1sv5ewje8sm80r9",
    "95mp2snular2q0j2irih6ht": "hgfihscw1sv5ewje8sm80r9",
    "09edenuzuoqp22bxje5l36y": "zkfccjgcs7b7pqvirwby57p",
    "ik9twe6vf70yht7mt79j88t": "09edenuzuoqp22bxje5l36y",
    "n0j2ootma2fifoxdm24zs2e": "ik9twe6vf70yht7mt79j88t",
    "nx5lgbcvbdsmx43eu1jujpt": "ik9twe6vf70yht7mt79j88t",
    "218js88kimcujeri1kdql6t": "ik9twe6vf70yht7mt79j88t",
    "q73ywmrtq7srqjbs0jjzxm2": "218js88kimcujeri1kdql6t",
    "jnfxsw50aav1bist3xdmb36": "218js88kimcujeri1kdql6t",
    "w9h2yeqs0gc5da00dbw690j": "ik9twe6vf70yht7mt79j88t",
    "o7lmvujajn5mr0cyficoef5": "ik9twe6vf70yht7mt79j88t",
    "ex5lcezatpfmu8p97fgbey7": "ik9twe6vf70yht7mt79j88t",
    "gl5xjjjpsuuiazam6swp1qp": "09edenuzuoqp22bxje5l36y",
    "peaxf97kpd4jafg9wekcaz8": "gl5xjjjpsuuiazam6swp1qp",
    "s3mhgxb78z7jyifmzp1hsd3": "gl5xjjjpsuuiazam6swp1qp",
    "grym4gsk3se3limyrf8uoip": "gl5xjjjpsuuiazam6swp1qp",
    "3x98jnnbdtk4yacyr4wpefc": "gl5xjjjpsuuiazam6swp1qp",
    "a4d445e0o55ndcozlhkwqfz": "zkfccjgcs7b7pqvirwby57p",
    "olp8vo3frywt998l6h1f3ws": "a4d445e0o55ndcozlhkwqfz",
    "0qxb469esdfnckmc3254mmp": "zkfccjgcs7b7pqvirwby57p",
    "m75y7l3tusc1xrp3atjv1jz": "0qxb469esdfnckmc3254mmp"
  },
  "notesLabelById": {
    "zkfccjgcs7b7pqvirwby57p": "Web Components",
    "3902657y6cqngtzx4irs133": "Apis",
    "1dym5u9edx4r2i85mmldv4m": "custom-elements",
    "efwvmwe8ctv925mkt5wrl5z": "shadow-dom",
    "d9i2loe47cp2m0xxwdkny69": "content-slot",
    "lf0t5f3evkower2vnkbazq5": "template",
    "jz2mgtp1h1frnrzmeqocl36": "Communication",
    "6ru1efirtn5teux1y43551d": "JS Properties",
    "tnijj658ufqhea7vlwft2r9": "Custom Attributes",
    "h8e4ccyda8x2xn10jqv3qb2": "Events",
    "f1sy95vvl2cyfpto8miwxhh": "Styling",
    "fcj7t4u5hm6t7amh45uid1n": "CSS Encapsulation",
    "5vihc22zv3ux3lduf3aaab6": "CSS Custom Properties",
    "lgs19vv9v8nq2megefqyprn": "CSS Parts API",
    "3lzfo9vm01y09nvjbji1g25": "Slotted Elements",
    "wulm1e3c9d69le8k1pa5lxh": "Theming",
    "kguufsu71atg67ixw875jy1": "Root Host Scope",
    "gxmnngmtnylxfipxr0980ej": "Lifecycle",
    "uw1ie7bctc50l5lz3cytw4i": "Constructor Connected Callback",
    "37nsf4f13y89b6j5pgbmd9o": "Attribute Changed",
    "u5xmw029xvzv9yc7s3o152j": "Disconnected Callback",
    "iqbswjrdrlwkkca05u33nov": "Adopted Callback",
    "a3xw0se9vtlbizvaguc85sw": "Hierarchy and Architecture",
    "nz23kt8zcx99qr9ei3td0kg": "Component Data Flow",
    "1mhjcs0yb8e8xp0x1g030qq": "Deployment",
    "pizkajsyb0lra3nyjuiueiq": "Npm",
    "l1ofcgjdkle0j55lk21ujrq": "Browser Support",
    "hgfihscw1sv5ewje8sm80r9": "Frameworks Integration",
    "3m8fv43uyem4l9uc3y7780z": "Angular",
    "tqrfdzuafg2zfze5bj19sns": "React",
    "95mp2snular2q0j2irih6ht": "Vue",
    "09edenuzuoqp22bxje5l36y": "High Level Solutions",
    "ik9twe6vf70yht7mt79j88t": "Lit",
    "n0j2ootma2fifoxdm24zs2e": "Binding Components",
    "nx5lgbcvbdsmx43eu1jujpt": "Custom Events",
    "218js88kimcujeri1kdql6t": "Examples",
    "q73ywmrtq7srqjbs0jjzxm2": "Todo App",
    "jnfxsw50aav1bist3xdmb36": "Unit Testing",
    "w9h2yeqs0gc5da00dbw690j": "Properties and Decorators",
    "o7lmvujajn5mr0cyficoef5": "Template Event Listeners",
    "ex5lcezatpfmu8p97fgbey7": "Template Strings",
    "gl5xjjjpsuuiazam6swp1qp": "Stencil",
    "peaxf97kpd4jafg9wekcaz8": "Building",
    "s3mhgxb78z7jyifmzp1hsd3": "Component Bindings",
    "grym4gsk3se3limyrf8uoip": "Decorators",
    "3x98jnnbdtk4yacyr4wpefc": "JSX Templates",
    "a4d445e0o55ndcozlhkwqfz": "Examples",
    "olp8vo3frywt998l6h1f3ws": "Dropdown",
    "0qxb469esdfnckmc3254mmp": "Extra Tools",
    "m75y7l3tusc1xrp3atjv1jz": "Webpack"
  }
}
